AuthenticationMiddleWare/__init__.py
AuthenticationMiddleWare/access_control.py
AuthenticationMiddleWare/logger.py
AuthenticationMiddleWare/middleware.py
AuthenticationMiddleWare/tracing_middleware.py
pybase_library-1.0.5.dist-info/METADATA
pybase_library-1.0.5.dist-info/WHEEL
pybase_library-1.0.5.dist-info/top_level.txt
pybase_library-1.0.5.dist-info/RECORD
