Metadata-Version: 2.4
Name: pybase_library
Version: 1.0.5
Summary: Python based library
Author: thinhnt3
Requires-Python: >=3.11
Dynamic: author
Dynamic: requires-python
Dynamic: summary
